juq/__init__.py
juq/cells.py
juq/cli.py
juq/fmt.py
juq/main.py
juq/merge_outputs.py
juq/renumber.py
juq/papermill/__init__.py
juq/papermill/clean.py
juq/papermill/run.py
juq_py-0.7.0.dist-info/METADATA
juq_py-0.7.0.dist-info/WHEEL
juq_py-0.7.0.dist-info/entry_points.txt
juq_py-0.7.0.dist-info/RECORD
