Metadata-Version: 2.4
Name: juq_py
Version: 0.7.0
Summary: Query, run, and clean/normalize Jupyter notebooks
Project-URL: Homepage, https://github.com/runsascoded/juq
Project-URL: Author, https://github.com/ryan-williams
Author-email: Ryan Williams <ryan@runsascoded.com>
License: MIT
Classifier: License :: OSI Approved :: MIT License
Classifier: Operating System :: OS Independent
Classifier: Programming Language :: Python :: 3
Requires-Python: >=3.9
Requires-Dist: click
Requires-Dist: nbformat
Requires-Dist: utz>=0.16.1
Provides-Extra: test
Requires-Dist: ipykernel; extra == 'test'
Requires-Dist: papermill; extra == 'test'
Requires-Dist: pytest; extra == 'test'
